[
  {
    "toyId": 1,
    "toyName": "All Data",
    "sellerName": "Toys R Us Local",
    "sellerEmail": "contact@toysruslocal.com",
    "price": 49.99,
    "rating": 4.7,
    "availableQuantity": 75,
    "description": "A timeless set of colorful Lego bricks that encourages creativity and problem-solving. Kids can build anything they imagine, from houses to vehicles.",
    "pictureURL": "https://i.ibb.co.com/4n4nhYrN/hero-img-3.webp",
    "subCategory": "Building Blocks"
  },
  {
    "toyId": 2,
    "toyName": "Hot Wheels Super Track Set",
    "sellerName": "Speedy Toys Hub",
    "sellerEmail": "sales@speedytoyshub.com",
    "price": 34.5,
    "rating": 4.5,
    "availableQuantity": 60,
    "description": "A thrilling car racing track with loops and jumps. Includes two die-cast cars and a launcher for endless racing fun.",
    "pictureURL": "https://i.ibb.co.com/7NCr5BPs/img-5.jpg",
    "subCategory": "Toy Vehicles"
  },
  {
    "toyId": 3,
    "toyName": "Barbie Dream House",
    "sellerName": "DollWorld Store",
    "sellerEmail": "info@dollworldstore.com",
    "price": 119.99,
    "rating": 4.8,
    "availableQuantity": 40,
    "description": "A luxurious Barbie house featuring three stories, furniture, and accessories. Perfect for imaginative role play.",
    "pictureURL": "https://i.ibb.co.com/7t9dppRb/img-6.jpg",
    "subCategory": "Dolls & Accessories"
  },
  {
    "toyId": 4,
    "toyName": "Nerf Elite Blaster",
    "sellerName": "Blaster Zone",
    "sellerEmail": "orders@blasterzone.com",
    "price": 29.99,
    "rating": 4.3,
    "availableQuantity": 90,
    "description": "A high-performance Nerf gun for fast-paced action. Shoots darts up to 90 feet for exciting outdoor play.",
    "pictureURL": "https://i.ibb.co.com/KcxyHjBj/hero-img2.webp",
    "subCategory": "Action Toys"
  },
  {
    "toyId": 5,
    "toyName": "Play-Doh Mega Fun Set",
    "sellerName": "Creative Kids Mart",
    "sellerEmail": "support@creativekidsmart.com",
    "price": 19.99,
    "rating": 4.6,
    "availableQuantity": 120,
    "description": "A colorful Play-Doh set with molds, cutters, and 10 vibrant dough tubs. Great for kids’ creativity and motor skills.",
    "pictureURL": "https://i.ibb.co.com/xqQGWdtD/hero-img.webp",
    "subCategory": "Arts & Crafts"
  },
  {
    "toyId": 6,
    "toyName": "RC Monster Truck",
    "sellerName": "Remote Riders",
    "sellerEmail": "help@remoteriders.com",
    "price": 59.99,
    "rating": 4.4,
    "availableQuantity": 55,
    "description": "A durable remote-controlled monster truck with 4x4 power and shock suspension for off-road adventures.",
    "pictureURL": "https://i.ibb.co.com/twPWP4XX/img-2.jpg",
    "subCategory": "Remote Control Toys"
  },
  {
    "toyId": 7,
    "toyName": "Puzzle World Map",
    "sellerName": "Brainy Kids Zone",
    "sellerEmail": "contact@brainykidszone.com",
    "price": 24.99,
    "rating": 4.9,
    "availableQuantity": 80,
    "description": "An educational 100-piece puzzle featuring a colorful world map. Helps children learn geography while having fun.",
    "pictureURL": "https://i.ibb.co.com/JW4vrPdz/img-3.jpg",
    "subCategory": "Educational Toys"
  },
  {
    "toyId": 8,
    "toyName": "Stuffed Teddy Bear",
    "sellerName": "Cuddle Corner",
    "sellerEmail": "shop@cuddlecorner.com",
    "price": 27.5,
    "rating": 4.8,
    "availableQuantity": 100,
    "description": "A soft, huggable teddy bear made of premium cotton plush. Perfect for gifting and comforting young children.",
    "pictureURL": "https://i.ibb.co.com/RnFDYd4/hero-img4.webp",
    "subCategory": "Soft Toys"
  },
  {
    "toyId": 9,
    "toyName": "Magnetic Building Tiles",
    "sellerName": "Smart Play Store",
    "sellerEmail": "support@smartplay.com",
    "price": 44.99,
    "rating": 4.8,
    "availableQuantity": 85,
    "description": "A colorful set of magnetic tiles that lets kids build castles, cars, and creative 3D structures safely and easily.",
    "pictureURL": "https://i.ibb.co.com/DPHN5gZQ/img-8.jpg",
    "subCategory": "STEM Toys"
  },
  {
    "toyId": 10,
    "toyName": "Wooden Train Set",
    "sellerName": "Tiny Tracks Co.",
    "sellerEmail": "info@tinytracks.com",
    "price": 39.99,
    "rating": 4.7,
    "availableQuantity": 70,
    "description": "Classic wooden train set with tracks, tunnels, and bridges. Encourages fine motor skills and creative play.",
    "pictureURL": "https://i.ibb.co.com/F44FpHVd/img-7.jpg",
    "subCategory": "Wooden Toys"
  },
  {
    "toyId": 11,
    "toyName": "Dinosaur Explorer Kit",
    "sellerName": "Jurassic Juniors",
    "sellerEmail": "hello@jurassicjuniors.com",
    "price": 32.5,
    "rating": 4.5,
    "availableQuantity": 65,
    "description": "Dig up fossils, study dinosaurs, and learn prehistory in a fun interactive kit with toy fossils and brushes.",
    "pictureURL": "https://i.ibb.co.com/twPWP4XX/img-2.jpg",
    "subCategory": "Educational Toys"
  },
  {
    "toyId": 12,
    "toyName": "Mini Kitchen Playset",
    "sellerName": "Home Chef Kids",
    "sellerEmail": "kitchen@homechefkids.com",
    "price": 54.99,
    "rating": 4.6,
    "availableQuantity": 90,
    "description": "A cute pink kitchen playset with utensils, stove, and mini oven. Great for kids’ pretend cooking fun.",
    "pictureURL": "https://i.ibb.co.com/7xLYRs9j/side-imge3.webp",
    "subCategory": "Role Play Toys"
  },
  {
    "toyId": 13,
    "toyName": "Space Rocket Model Kit",
    "sellerName": "Astro Kids",
    "sellerEmail": "space@astrokids.com",
    "price": 42.99,
    "rating": 4.9,
    "availableQuantity": 50,
    "description": "Build your own rocket model! A fun STEM-based kit for future astronauts and engineers.",
    "pictureURL": "https://i.ibb.co.com/tTsQB1RS/side-toys.webp",
    "subCategory": "STEM Toys"
  },
  {
    "toyId": 14,
    "toyName": "Animal Figurine Pack",
    "sellerName": "Nature Play Toys",
    "sellerEmail": "sales@natureplay.com",
    "price": 22.99,
    "rating": 4.4,
    "availableQuantity": 110,
    "description": "A pack of realistic animal figures including lions, elephants, and zebras. Great for learning and play.",
    "pictureURL": "https://i.ibb.co.com/DPHN5gZQ/img-8.jpg",
    "subCategory": "Educational Toys"
  },
  {
    "toyId": 15,
    "toyName": "Bubble Maker Machine",
    "sellerName": "Outdoor Joy",
    "sellerEmail": "contact@outdoorjoy.com",
    "price": 18.5,
    "rating": 4.3,
    "availableQuantity": 150,
    "description": "Automatic bubble maker that creates hundreds of colorful bubbles in seconds. Perfect for outdoor fun.",
    "pictureURL": "https://i.ibb.co.com/7NCr5BPs/img-5.jpg",
    "subCategory": "Outdoor Toys"
  },
  {
    "toyId": 16,
    "toyName": "Musical Xylophone Set",
    "sellerName": "Melody Kids",
    "sellerEmail": "info@melodykids.com",
    "price": 26.99,
    "rating": 4.7,
    "availableQuantity": 95,
    "description": "Brightly colored metal xylophone that produces real musical notes. Great for early sound learning.",
    "pictureURL": "https://i.ibb.co.com/KcxyHjBj/hero-img2.webp",
    "subCategory": "Musical Toys"
  }
]
